yby_list/__init__.py
yby_list-0.0.1.dist-info/LICENSE.txt
yby_list-0.0.1.dist-info/METADATA
yby_list-0.0.1.dist-info/WHEEL
yby_list-0.0.1.dist-info/top_level.txt
yby_list-0.0.1.dist-info/RECORD
