Metadata-Version: 2.1
Name: yby-list
Version: 0.0.1
Summary: yanbingyang personal packages
Home-page: https://pypi.org/user/Flyby_98/
Author: Bingyang Yan
Author-email: yanbingyang1998@outlook.com
License: Copyright (c) 2022 The Python Packaging Authority         
Platform: UNKNOWN
Classifier: Programming Language :: Python :: 3
Classifier: License :: OSI Approved :: MIT License
Classifier: Operating System :: OS Independent
Requires-Python: >=3.6
License-File: LICENSE.txt
Requires-Dist: pyqt5
Requires-Dist: h5py
Requires-Dist: mayavi
Requires-Dist: numpy
Requires-Dist: scipy
Requires-Dist: pandas
Requires-Dist: glob2
Requires-Dist: jupyter
Requires-Dist: jupyterlab
Requires-Dist: matplotlib
Requires-Dist: openpyxl
Requires-Dist: sklearn
Requires-Dist: scikit-opt
Requires-Dist: tqdm
Requires-Dist: torch
Requires-Dist: tensorboard
Requires-Dist: vtk
